gofilepy/__init__.py
gofilepy/exceptions.py
gofilepy/gofile.py
gofilepy/options.py
gofilepy_api-0.2.9.dist-info/LICENSE.txt
gofilepy_api-0.2.9.dist-info/METADATA
gofilepy_api-0.2.9.dist-info/WHEEL
gofilepy_api-0.2.9.dist-info/top_level.txt
gofilepy_api-0.2.9.dist-info/RECORD
