Metadata-Version: 2.1
Name: gofilepy-api
Version: 0.2.9
Summary: A python wrapper for Gofile REST API
Home-page: https://github.com/m0bb1n/gofilepy
Author: m0bb1n
Author-email: 99den0@gmail.com
License: MIT
Platform: UNKNOWN
Classifier: Programming Language :: Python :: 3
Classifier: Programming Language :: Python :: 3.10
License-File: LICENSE.txt
Requires-Dist: requests
